qiitacli/__init__.py
qiitacli/accesstoken.py
qiitacli/client.py
qiitacli/exceptions.py
qiitacli/option_parser.py
tests/__init__.py
tests/test_accesstoken.py
tests/test_client.py
tests/test_delete.py
tests/test_list.py
tests/test_option_parser.py
tests/test_status.py
tests/test_update.py
tests/test_upload.py
qiitacli-1.1.0.dist-info/LICENSE
qiitacli-1.1.0.dist-info/METADATA
qiitacli-1.1.0.dist-info/WHEEL
qiitacli-1.1.0.dist-info/entry_points.txt
qiitacli-1.1.0.dist-info/top_level.txt
qiitacli-1.1.0.dist-info/RECORD
