Metadata-Version: 2.1
Name: qiitacli
Version: 1.1.0
Summary: CLI Application for Qiita API v2
Home-page: https://github.com/mypaceshun/qiitacli
Author: KAWAI Shun
Author-email: shun@osstech.co.jp
Maintainer: KAWAI Shun
Maintainer-email: shun@osstech.co.jp
License: MIT
Platform: UNKNOWN
Requires-Dist: click (>=7.0)
Requires-Dist: qiita-v2 (>=0.2.1)
